azure/mgmt/springappdiscovery/__init__.py
azure/mgmt/springappdiscovery/_configuration.py
azure/mgmt/springappdiscovery/_patch.py
azure/mgmt/springappdiscovery/_serialization.py
azure/mgmt/springappdiscovery/_spring_app_discovery_mgmt_client.py
azure/mgmt/springappdiscovery/_vendor.py
azure/mgmt/springappdiscovery/_version.py
azure/mgmt/springappdiscovery/py.typed
azure/mgmt/springappdiscovery/aio/__init__.py
azure/mgmt/springappdiscovery/aio/_configuration.py
azure/mgmt/springappdiscovery/aio/_patch.py
azure/mgmt/springappdiscovery/aio/_spring_app_discovery_mgmt_client.py
azure/mgmt/springappdiscovery/aio/operations/__init__.py
azure/mgmt/springappdiscovery/aio/operations/_error_summaries_operations.py
azure/mgmt/springappdiscovery/aio/operations/_operations.py
azure/mgmt/springappdiscovery/aio/operations/_patch.py
azure/mgmt/springappdiscovery/aio/operations/_springbootapps_operations.py
azure/mgmt/springappdiscovery/aio/operations/_springbootservers_operations.py
azure/mgmt/springappdiscovery/aio/operations/_springbootsites_operations.py
azure/mgmt/springappdiscovery/aio/operations/_summaries_operations.py
azure/mgmt/springappdiscovery/models/__init__.py
azure/mgmt/springappdiscovery/models/_models_py3.py
azure/mgmt/springappdiscovery/models/_patch.py
azure/mgmt/springappdiscovery/models/_spring_app_discovery_mgmt_client_enums.py
azure/mgmt/springappdiscovery/operations/__init__.py
azure/mgmt/springappdiscovery/operations/_error_summaries_operations.py
azure/mgmt/springappdiscovery/operations/_operations.py
azure/mgmt/springappdiscovery/operations/_patch.py
azure/mgmt/springappdiscovery/operations/_springbootapps_operations.py
azure/mgmt/springappdiscovery/operations/_springbootservers_operations.py
azure/mgmt/springappdiscovery/operations/_springbootsites_operations.py
azure/mgmt/springappdiscovery/operations/_summaries_operations.py
azure_mgmt_springappdiscovery-1.0.0b1.dist-info/LICENSE
azure_mgmt_springappdiscovery-1.0.0b1.dist-info/METADATA
azure_mgmt_springappdiscovery-1.0.0b1.dist-info/WHEEL
azure_mgmt_springappdiscovery-1.0.0b1.dist-info/top_level.txt
azure_mgmt_springappdiscovery-1.0.0b1.dist-info/RECORD
